istatistik/__init__.py
istatistik/istatistik.py
istatistik-0.2.dist-info/DESCRIPTION.rst
istatistik-0.2.dist-info/METADATA
istatistik-0.2.dist-info/RECORD
istatistik-0.2.dist-info/WHEEL
istatistik-0.2.dist-info/metadata.json
istatistik-0.2.dist-info/top_level.txt
