Metadata-Version: 2.0
Name: istatistik
Version: 0.2
Summary: Statistics module for learning purposes.
Home-page: https://github.com/yavuzovski/playground/tree/master/school_3(C%2C%20C%23%2C%20Python)/%C3%96dev/seriler
Author: Oğuzcan Yavuz
Author-email: oguzcanyavuz321@gmail.com
License: GPLv3
Platform: UNKNOWN
